anabrid/redaccess/api/client/__init__.py
anabrid/redaccess/api/client/gen/__init__.py
anabrid/redaccess/api/client/gen/api_client.py
anabrid/redaccess/api/client/gen/api_response.py
anabrid/redaccess/api/client/gen/configuration.py
anabrid/redaccess/api/client/gen/exceptions.py
anabrid/redaccess/api/client/gen/jobs_api.py
anabrid/redaccess/api/client/gen/rest.py
anabrid/redaccess/api/client/gen/system_api.py
anabrid/redaccess/api/client/job_bundle.py
anabrid/redaccess/api/client/job_user_callbacks.py
anabrid/redaccess/api/client/lucipy_import.py
anabrid/redaccess/api/client/redac_client.py
anabrid/redaccess/api/client/redacli.py
anabrid_redac_client-0.1.3.dist-info/METADATA
anabrid_redac_client-0.1.3.dist-info/WHEEL
anabrid_redac_client-0.1.3.dist-info/entry_points.txt
anabrid_redac_client-0.1.3.dist-info/RECORD
