Metadata-Version: 2.1
Name: anabrid-redac-client
Version: 0.1.3
Summary: Client module for REDAC project's software infrastructure
License: 3BSD
Author: Daniel Thuerck
Author-email: thuerck@anabrid.com
Requires-Python: >=3.10,<4.0
Classifier: License :: Other/Proprietary License
Classifier: Programming Language :: Python :: 3
Classifier: Programming Language :: Python :: 3.10
Classifier: Programming Language :: Python :: 3.11
Classifier: Programming Language :: Python :: 3.12
Requires-Dist: aiohttp (>=3.11.12,<4.0.0)
Requires-Dist: anabrid-redac-core (>=0.1.0,<0.2.0)
Requires-Dist: lucipy (>=1.6.0,<2.0.0)
Requires-Dist: matplotlib (>=3.10.0,<4.0.0)
Requires-Dist: python-dateutil (>=2.9.0.post0,<3.0.0)
Requires-Dist: requests (>=2.32.3,<3.0.0)
Requires-Dist: typer (>=0.15.1,<0.16.0)
Requires-Dist: urllib3 (>=2.3.0,<3.0.0)
Requires-Dist: yaspin (>=3.1.0,<4.0.0)
